dryfalls/LICENSE.template
dryfalls/Pipfile.lock.template
dryfalls/Pipfile.template
dryfalls/README.md.template
dryfalls/__init__.py
dryfalls/__init__.py.template
dryfalls/__main__.py
dryfalls/__main__.py.template
dryfalls/bld.bat.template
dryfalls/build.sh.template
dryfalls/config.template
dryfalls/gitignore.template
dryfalls/initpy.template
dryfalls/meta.yaml.template
dryfalls/repotemplate.json
dryfalls/setup.py.template
dryfalls/travistest.template
dryfalls/utils.py
dryfalls-0.0.14.dist-info/LICENSE
dryfalls-0.0.14.dist-info/METADATA
dryfalls-0.0.14.dist-info/WHEEL
dryfalls-0.0.14.dist-info/entry_points.txt
dryfalls-0.0.14.dist-info/top_level.txt
dryfalls-0.0.14.dist-info/RECORD
