Metadata-Version: 2.1
Name: dryfalls
Version: 0.0.14
Summary: test project
Home-page: https://github.com/pythonflaskserverapps/dryfalls
Author: pythonflaskserverapps
Author-email: pythonflaskserverapps@gmail.com
License: MIT
Keywords: test project
Platform: UNKNOWN
Classifier: Development Status :: 5 - Production/Stable
Classifier: Intended Audience :: Developers
Classifier: Programming Language :: Python :: 3
Classifier: Programming Language :: Python :: 3.6
Requires-Python: >=3.6
Requires-Dist: pyyaml (==3.13)
Requires-Dist: pygithub (==1.43.5)
